gpugpu/__init__.py
gpugpu/__main__.py
gpugpu/gpus.py
gpugpu/utils.py
gpugpu-1.0.2.dist-info/METADATA
gpugpu-1.0.2.dist-info/WHEEL
gpugpu-1.0.2.dist-info/top_level.txt
gpugpu-1.0.2.dist-info/RECORD
