Metadata-Version: 2.1
Name: gpugpu
Version: 1.0.2
Summary: gpugpu shows current statistics of GPUs and memory usage by running containers
Home-page: https://github.com/jonghwanhyeon/gpugpu
Author: Jonghwan Hyeon
Author-email: jonghwanhyeon93@gmail.com
License: MIT
Keywords: gpu,usage,docker,container
Classifier: Development Status :: 4 - Beta
Classifier: Programming Language :: Python :: 3
Classifier: Programming Language :: Python :: 3.7
Classifier: Programming Language :: Python :: 3.8
Classifier: Programming Language :: Python :: 3 :: Only
Requires-Dist: colored
Requires-Dist: docker
Requires-Dist: nvidia-ml-py3
Requires-Dist: psutil
